LICENSE
MANIFEST.in
README.md
setup.py
qupid/__init__.py
qupid/_casematch_utils.py
qupid/_descriptions.py
qupid/_exceptions.py
qupid/casematch.py
qupid/decorators.py
qupid/matching.py
qupid/qupid.py
qupid/stats.py
qupid/utils.py
qupid.egg-info/PKG-INFO
qupid.egg-info/SOURCES.txt
qupid.egg-info/dependency_links.txt
qupid.egg-info/entry_points.txt
qupid.egg-info/requires.txt
qupid.egg-info/top_level.txt
qupid/cli/cli.py
qupid/q2/__init__.py
qupid/q2/_format.py
qupid/q2/_methods.py
qupid/q2/_pipelines.py
qupid/q2/_transformer.py
qupid/q2/_type.py
qupid/q2/_visualizers.py
qupid/q2/plugin_setup.py
qupid/tests/test_casematch.py
qupid/tests/test_casematch_utils.py
qupid/tests/test_cli.py
qupid/tests/test_matching.py
qupid/tests/test_qupid.py
qupid/tests/test_stats.py
qupid/tests/test_utils.py
qupid/tests/data/asd.tsv
qupid/tests/data/test.json
qupid/tests/data/test.tsv